asgi_lifespan/__init__.py
asgi_lifespan/_compat.py
asgi_lifespan/_exceptions.py
asgi_lifespan/_manager.py
asgi_lifespan/_types.py
asgi_lifespan/py.typed
asgi_lifespan/_concurrency/__init__.py
asgi_lifespan/_concurrency/asyncio.py
asgi_lifespan/_concurrency/base.py
asgi_lifespan/_concurrency/trio.py
asgi_lifespan-2.1.0.dist-info/LICENSE
asgi_lifespan-2.1.0.dist-info/METADATA
asgi_lifespan-2.1.0.dist-info/WHEEL
asgi_lifespan-2.1.0.dist-info/top_level.txt
asgi_lifespan-2.1.0.dist-info/RECORD
