Metadata-Version: 2.1
Name: asgi-lifespan
Version: 2.1.0
Summary: Programmatic startup/shutdown of ASGI apps.
Author-email: Florimond Manca <florimond.manca@protonmail.com>
License: MIT
Project-URL: Homepage, https://github.com/florimondmanca/asgi-lifespan
Classifier: Development Status :: 5 - Production/Stable
Classifier: Intended Audience :: Developers
Classifier: Framework :: AsyncIO
Classifier: Framework :: Trio
Classifier: Programming Language :: Python :: 3
Classifier: Programming Language :: Python :: 3 :: Only
Classifier: Programming Language :: Python :: 3.7
Classifier: Programming Language :: Python :: 3.8
Classifier: Programming Language :: Python :: 3.9
Classifier: Programming Language :: Python :: 3.10
Classifier: Programming Language :: Python :: 3.11
Requires-Python: >=3.7
License-File: LICENSE
